convertfiletovoice2/__init__.py
convertfiletovoice2/convertfiletovoice.py
convertfiletovoice2-0.1.dist-info/LICENSE
convertfiletovoice2-0.1.dist-info/METADATA
convertfiletovoice2-0.1.dist-info/WHEEL
convertfiletovoice2-0.1.dist-info/top_level.txt
convertfiletovoice2-0.1.dist-info/RECORD
