Metadata-Version: 2.1
Name: convertfiletovoice2
Version: 0.1
Summary: convert file to voice
Author: MarkoKoval <marko.koval.work@gmail.com>
License-File: LICENSE
Requires-Dist: pyttsx3
